pyobjfile/__about__.py
pyobjfile/__init__.py
pyobjfile/elf.py
pyobjfile/mach_o.py
pyobjfile/mach_o_tk.py
pyobjfile/util/__about__.py
pyobjfile/util/__init__.py
pyobjfile/util/dict_utils.py
pyobjfile/util/file_extract.py
pyobjfile/util/shortencpp.py
pyobjfile/util/term_colors.py
pyobjfile/util/ver.py
py_object_file-0.2.2b5.dist-info/METADATA
py_object_file-0.2.2b5.dist-info/WHEEL
py_object_file-0.2.2b5.dist-info/top_level.txt
py_object_file-0.2.2b5.dist-info/RECORD
