Metadata-Version: 2.1
Name: py-object-file
Version: 0.2.2b5
Summary: A package to parse exutable and library object files, such as ELF and Mach-O.
Home-page: https://github.com/zcutlip/py-object-file
License: UNKNOWN
Platform: UNKNOWN
Requires-Python: >=3.7
